tests/__init__.py
tests/test_editor.py
yunji/__init__.py
yunji/editor.py
yunji/temp.py
yunji/images/add.png
yunji/images/add_g.png
yunji/images/editor.png
yunji/images/editor_.png
yunji/images/font-size.png
yunji/images/open.png
yunji/images/save.png
yunji/images/save_as.png
yunji/images/setting-two.png
yunji/images/setting.png
yunji-0.4.dist-info/LICENSE
yunji-0.4.dist-info/METADATA
yunji-0.4.dist-info/WHEEL
yunji-0.4.dist-info/entry_points.txt
yunji-0.4.dist-info/top_level.txt
yunji-0.4.dist-info/RECORD
