Metadata-Version: 2.1
Name: yunji
Version: 0.4
Summary: A PyQt5-based text editor
Home-page: https://github.com/YSP0Github/yunji.git
Author: Yun Song
Author-email: ysp@cug.edu.cn
Classifier: Programming Language :: Python :: 3
Classifier: License :: OSI Approved :: MIT License
Classifier: Operating System :: OS Independent
Requires-Python: >=3.6
License-File: LICENSE
Requires-Dist: PyQt5
Requires-Dist: chardet
